pgsql/__init__.py
pgsql/client.py
pgsql/opslib/pgsql/__init__.py
pgsql/opslib/pgsql/client.py
ops_lib_pgsql-1.4.dist-info/LICENSE
ops_lib_pgsql-1.4.dist-info/METADATA
ops_lib_pgsql-1.4.dist-info/WHEEL
ops_lib_pgsql-1.4.dist-info/top_level.txt
ops_lib_pgsql-1.4.dist-info/RECORD
