Metadata-Version: 2.1
Name: ops-lib-pgsql
Version: 1.4
Summary: PostgreSQL database relation for Juju Operator Framework Charms
Home-page: https://github.com/canonical/ops-lib-pgsql
Author: Stuart Bishop
Author-email: stuart.bishop@canonical.com
Maintainer: PostgreSQL Charmers
Maintainer-email: postgresql-charmers@lists.launchpad.net
License: UNKNOWN
Project-URL: Juju, https://juju.is/
Project-URL: Juju Operator Framework, https://pypi.org/project/ops/
Keywords: juju charm opslib postgres postgresql pgsql
Platform: UNKNOWN
Classifier: Development Status :: 5 - Production/Stable
Classifier: Programming Language :: Python :: 3 :: Only
Classifier: Programming Language :: Python :: 3.6
Classifier: Programming Language :: Python :: 3.7
Classifier: Programming Language :: Python :: 3.8
Classifier: Programming Language :: Python :: 3.9
Classifier: License :: OSI Approved :: GNU Lesser General Public License v3 (LGPLv3)
Classifier: Operating System :: OS Independent
Requires-Python: >=3.6
Requires-Dist: ops (>=0.8.0)
Requires-Dist: PyYAML
Requires-Dist: pgconnstr
